iiif_download/__init__.py
iiif_download/cli.py
iiif_download/config.py
iiif_download/image.py
iiif_download/manifest.py
iiif_download/tests/__init__.py
iiif_download/tests/conftest.py
iiif_download/tests/test_config.py
iiif_download/tests/test_image.py
iiif_download/tests/test_manifest.py
iiif_download/tests/fixtures/manifest_empty.json
iiif_download/tests/fixtures/manifest_test.json
iiif_download/tests/fixtures/manifest_v2.json
iiif_download/tests/fixtures/manifest_v3.json
iiif_download/utils/__init__.py
iiif_download/utils/logger.py
iiif_download-0.1.14.dist-info/licenses/LICENSE
iiif_download-0.1.14.dist-info/METADATA
iiif_download-0.1.14.dist-info/WHEEL
iiif_download-0.1.14.dist-info/entry_points.txt
iiif_download-0.1.14.dist-info/top_level.txt
iiif_download-0.1.14.dist-info/RECORD
