Metadata-Version: 2.4
Name: iiif-download
Version: 0.1.14
Summary: A Python package to download images from IIIF manifests
Author-email: Segolene-Albouy <segolene.albouy@gmail.com>
Project-URL: Homepage, https://github.com/Segolene-Albouy/iiif-download
Project-URL: Documentation, https://github.com/Segolene-Albouy/iiif-download#readme
Project-URL: Repository, https://github.com/Segolene-Albouy/iiif-download
Project-URL: Issues, https://github.com/Segolene-Albouy/iiif-download/issues
Classifier: Development Status :: 3 - Alpha
Classifier: Intended Audience :: Developers
Classifier: Intended Audience :: Science/Research
Classifier: Programming Language :: Python :: 3
Classifier: Programming Language :: Python :: 3.8
Classifier: Programming Language :: Python :: 3.9
Classifier: Programming Language :: Python :: 3.10
Classifier: Programming Language :: Python :: 3.11
Classifier: Programming Language :: Python :: 3.12
Classifier: License :: OSI Approved :: MIT License
Requires-Python: >=3.8
License-File: LICENSE
Requires-Dist: Pillow>=11.0.0
Requires-Dist: requests>=2.32.0
Requires-Dist: tqdm>=4.66.0
Requires-Dist: urllib3>=2.2.0
Requires-Dist: aiohttp>=3.10
Requires-Dist: aiofiles>=24.1.0
Requires-Dist: rich>=13.9.0
Provides-Extra: dev
Requires-Dist: pytest>=8.0.0; extra == "dev"
Requires-Dist: pytest-cov>=6.0.0; extra == "dev"
Requires-Dist: pytest-asyncio>=0.25.0; extra == "dev"
Requires-Dist: ruff>=0.4.7; extra == "dev"
Requires-Dist: setuptools-scm>=9.2.0; extra == "dev"
Dynamic: license-file
